photons_core.py
photons_pytest.py
photons_app/__init__.py
photons_app/actions.py
photons_app/collector.py
photons_app/errors.py
photons_app/executor.py
photons_app/formatter.py
photons_app/helpers.py
photons_app/photons_app.py
photons_app/polyfill.py
photons_app/registers.py
photons_app/special.py
photons_app/mimic/__init__.py
photons_app/mimic/attrs.py
photons_app/mimic/device.py
photons_app/mimic/event.py
photons_app/mimic/operator.py
photons_app/mimic/packet_filter.py
photons_app/mimic/transport.py
photons_app/mimic/operators/__init__.py
photons_app/mimic/operators/clean.py
photons_app/mimic/operators/device.py
photons_app/mimic/operators/io.py
photons_app/mimic/operators/light.py
photons_app/mimic/operators/listener.py
photons_app/mimic/operators/matrix.py
photons_app/mimic/operators/multizone.py
photons_app/mimic/operators/relays.py
photons_app/tasks/__init__.py
photons_app/tasks/default_tasks.py
photons_app/tasks/register.py
photons_app/tasks/runner.py
photons_app/tasks/specifier.py
photons_app/tasks/tasks.py
photons_canvas/__init__.py
photons_canvas/addon.py
photons_canvas/orientation.py
photons_canvas/theme.py
photons_canvas/animations/__init__.py
photons_canvas/animations/action.py
photons_canvas/animations/lines.py
photons_canvas/animations/options.py
photons_canvas/animations/run_options.py
photons_canvas/animations/runner.py
photons_canvas/animations/infrastructure/__init__.py
photons_canvas/animations/infrastructure/animation.py
photons_canvas/animations/infrastructure/cannons.py
photons_canvas/animations/infrastructure/events.py
photons_canvas/animations/infrastructure/finish.py
photons_canvas/animations/infrastructure/register.py
photons_canvas/animations/infrastructure/state.py
photons_canvas/animations/registered/__init__.py
photons_canvas/animations/registered/balls.py
photons_canvas/animations/registered/color_cycle.py
photons_canvas/animations/registered/dice.py
photons_canvas/animations/registered/dots.py
lifx_photons_core-0.46.6.dist-info/METADATA
lifx_photons_core-0.46.6.dist-info/WHEEL
lifx_photons_core-0.46.6.dist-info/entry_points.txt
lifx_photons_core-0.46.6.dist-info/RECORD
